{
    "best_fitness": 18,
    "width": 4,
    "height": 4,
    "horizontal_links": [
        [
            1,
            1,
            1,
            -1
        ],
        [
            1,
            1,
            -1,
            1
        ],
        [
            -1,
            -1,
            -1,
            -1
        ],
        [
            1,
            1,
            -1,
            -1
        ]
    ],
    "vertical_links": [
        [
            1,
            -1,
            1,
            -1
        ],
        [
            -1,
            1,
            1,
            -1
        ],
        [
            -1,
            -1,
            1,
            1
        ],
        [
            1,
            -1,
            1,
            1
        ]
    ]
}